{"latitude":43.913517,"longitude":-79.80505,"generationtime_ms":0.8080005645751953,"utc_offset_seconds":-14400,"timezone":"America/New_York","timezone_abbreviation":"EDT","elevation":260.0,"current_weather":{"temperature":16.1,"windspeed":8.6,"winddirection":346.0,"weathercode":0,"is_day":0,"time":1683950400},"daily_units":{"time":"unixtime","weathercode":"wmo code","temperature_2m_max":"°C","temperature_2m_min":"°C","apparent_temperature_max":"°C","apparent_temperature_min":"°C","sunrise":"unixtime","sunset":"unixtime","precipitation_sum":"mm","rain_sum":"mm","showers_sum":"mm","snowfall_sum":"cm","precipitation_hours":"h","windspeed_10m_max":"km/h","windgusts_10m_max":"km/h","winddirection_10m_dominant":"°","shortwave_radiation_sum":"MJ/m²","et0_fao_evapotranspiration":"mm"},"daily":{"time":[1683950400,1684036800,1684123200,1684209600,1684296000,1684382400,1684468800],"weathercode":[0,2,0,1,2,2,3],"temperature_2m_max":[22.3,16.5,21.8,25.5,15.3,18.4,22.6],"temperature_2m_min":[11.7,6.4,4.7,11.6,5.2,1.7,6.7],"apparent_temperature_max":[22.3,14.3,19.2,23.3,13.0,16.8,22.0],"apparent_temperature_min":[8.1,2.7,1.0,8.0,1.0,-1.9,3.5],"sunrise":[1683971635,1684057966,1684144296,1684230636,1684316977,1684403317,1684489657],"sunset":[1684024631,1684111099,1684197568,1684284032,1684370496,1684456960,1684543425],"precipitation_sum":[0.00,0.00,0.00,0.00,0.00,0.00,0.00],"rain_sum":[0.00,0.00,0.00,0.00,0.00,0.00,0.00],"showers_sum":[0.00,0.00,0.00,0.00,0.00,0.00,0.00],"snowfall_sum":[0.00,0.00,0.00,0.00,0.00,0.00,0.00],"precipitation_hours":[0.0,0.0,0.0,0.0,0.0,0.0,0.0],"windspeed_10m_max":[15.1,15.1,17.3,23.8,15.5,10.1,9.4],"windgusts_10m_max":[37.1,27.7,45.4,58.7,34.9,15.5,16.6],"winddirection_10m_dominant":[356,0,286,285,11,115,131],"shortwave_radiation_sum":[28.48,27.30,29.63,28.40,29.89,28.86,26.11],"et0_fao_evapotranspiration":[5.46,4.80,6.14,7.23,4.82,4.77,4.81]}}