{"latitude":43.875,"longitude":-79.75,"generationtime_ms":1.0869503021240234,"utc_offset_seconds":-18000,"timezone":"America/New_York","timezone_abbreviation":"EST","elevation":257.0,"current_weather":{"temperature":-7.0,"windspeed":14.8,"winddirection":331.0,"weathercode":1,"time":1678579200},"daily_units":{"time":"unixtime","weathercode":"wmo code","temperature_2m_max":"°C","temperature_2m_min":"°C","apparent_temperature_max":"°C","apparent_temperature_min":"°C","sunrise":"unixtime","sunset":"unixtime","precipitation_sum":"mm","rain_sum":"mm","showers_sum":"mm","snowfall_sum":"cm","precipitation_hours":"h","windspeed_10m_max":"km/h","winddirection_10m_dominant":"°"},"daily":{"time":[1678510800,1678597200,1678683600,1678770000,1678856400,1678942800,1679029200],"weathercode":[71,71,71,3,3,61,73],"temperature_2m_max":[-2.0,-1.2,-0.3,-3.2,2.6,4.1,0.9],"temperature_2m_min":[-8.7,-12.6,-4.6,-8.0,-8.7,-0.9,-5.0],"apparent_temperature_max":[-6.6,-5.3,-4.7,-10.8,-2.0,0.9,-1.9],"apparent_temperature_min":[-12.8,-17.0,-10.3,-15.4,-14.7,-5.0,-10.2],"sunrise":[1678534619,1678620912,1678707204,1678793496,1678879789,1678966081,1679052372],"sunset":[1678576885,1678663360,1678749835,1678836309,1678922784,1679009258,1679095732],"precipitation_sum":[0.10,1.40,1.10,0.00,0.00,2.20,24.60],"rain_sum":[0.00,0.00,0.00,0.00,0.00,2.10,3.10],"showers_sum":[0.00,0.00,0.00,0.00,0.00,0.00,0.10],"snowfall_sum":[0.00,0.91,0.77,0.00,0.00,0.00,14.63],"precipitation_hours":[1.0,6.0,8.0,0.0,0.0,10.0,24.0],"windspeed_10m_max":[16.5,9.7,18.7,32.2,23.0,9.5,16.1],"winddirection_10m_dominant":[343,49,339,328,319,231,65]}}