{"latitude":43.913517,"longitude":-79.80505,"generationtime_ms":0.8169412612915039,"utc_offset_seconds":-14400,"timezone":"America/New_York","timezone_abbreviation":"EDT","elevation":260.0,"current_weather":{"temperature":4.6,"windspeed":9.4,"winddirection":182.0,"weathercode":3,"is_day":0,"time":1683000000},"daily_units":{"time":"unixtime","weathercode":"wmo code","temperature_2m_max":"°C","temperature_2m_min":"°C","apparent_temperature_max":"°C","apparent_temperature_min":"°C","sunrise":"unixtime","sunset":"unixtime","precipitation_sum":"mm","rain_sum":"mm","showers_sum":"mm","snowfall_sum":"cm","precipitation_hours":"h","windspeed_10m_max":"km/h","windgusts_10m_max":"km/h","winddirection_10m_dominant":"°","shortwave_radiation_sum":"MJ/m²","et0_fao_evapotranspiration":"mm"},"daily":{"time":[1683000000,1683086400,1683172800,1683259200,1683345600,1683432000,1683518400],"weathercode":[73,73,53,51,2,2,1],"temperature_2m_max":[6.5,11.4,14.5,14.8,19.0,21.6,22.5],"temperature_2m_min":[0.9,0.8,4.6,3.3,3.1,6.9,7.0],"apparent_temperature_max":[3.5,8.3,13.5,13.0,18.7,22.4,22.0],"apparent_temperature_min":[-2.1,-2.2,2.5,1.4,0.7,4.6,5.0],"sunrise":[1683022078,1683108395,1683194711,1683281026,1683367350,1683453673,1683539996],"sunset":[1683073467,1683159938,1683246409,1683332880,1683419350,1683505819,1683592288],"precipitation_sum":[7.50,9.00,1.00,0.40,0.00,0.00,0.00],"rain_sum":[6.20,8.70,1.00,0.40,0.00,0.00,0.00],"showers_sum":[0.00,0.00,0.00,0.00,0.00,0.00,0.00],"snowfall_sum":[0.70,0.84,0.00,0.00,0.00,0.00,0.00],"precipitation_hours":[9.0,15.0,4.0,4.0,0.0,0.0,0.0],"windspeed_10m_max":[9.4,16.6,9.0,5.8,5.0,5.0,11.5],"windgusts_10m_max":[21.6,38.2,19.4,11.5,14.4,9.7,16.2],"winddirection_10m_dominant":[221,345,9,156,356,341,173],"shortwave_radiation_sum":[7.45,12.50,20.39,16.14,25.75,24.33,26.88],"et0_fao_evapotranspiration":[1.03,1.57,2.79,2.32,4.08,4.16,4.79]}}