{"latitude":43.913517,"longitude":-79.80505,"generationtime_ms":0.9850263595581055,"utc_offset_seconds":-14400,"timezone":"America/New_York","timezone_abbreviation":"EDT","elevation":260.0,"current_weather":{"temperature":22.6,"windspeed":5.0,"winddirection":288.0,"weathercode":0,"is_day":1,"time":1683745200},"daily_units":{"time":"unixtime","weathercode":"wmo code","temperature_2m_max":"°C","temperature_2m_min":"°C","apparent_temperature_max":"°C","apparent_temperature_min":"°C","sunrise":"unixtime","sunset":"unixtime","precipitation_sum":"mm","rain_sum":"mm","showers_sum":"mm","snowfall_sum":"cm","precipitation_hours":"h","windspeed_10m_max":"km/h","windgusts_10m_max":"km/h","winddirection_10m_dominant":"°","shortwave_radiation_sum":"MJ/m²","et0_fao_evapotranspiration":"mm"},"daily":{"time":[1683691200,1683777600,1683864000,1683950400,1684036800,1684123200,1684209600],"weathercode":[2,3,3,1,1,1,51],"temperature_2m_max":[22.6,25.6,28.2,20.7,16.0,21.7,23.3],"temperature_2m_min":[5.5,10.2,13.1,11.7,8.3,4.5,8.8],"apparent_temperature_max":[23.2,26.2,29.8,19.6,13.6,19.4,20.7],"apparent_temperature_min":[1.9,7.4,11.4,8.4,4.2,1.1,4.3],"sunrise":[1683712642,1683798973,1683885304,1683971635,1684057966,1684144296,1684230636],"sunset":[1683765229,1683851696,1683938163,1684024631,1684111099,1684197568,1684284032],"precipitation_sum":[0.00,0.00,0.00,0.00,0.00,0.00,0.20],"rain_sum":[0.00,0.00,0.00,0.00,0.00,0.00,0.20],"showers_sum":[0.00,0.00,0.00,0.00,0.00,0.00,0.00],"snowfall_sum":[0.00,0.00,0.00,0.00,0.00,0.00,0.00],"precipitation_hours":[0.0,0.0,0.0,0.0,0.0,0.0,2.0],"windspeed_10m_max":[9.4,10.4,11.2,18.0,16.2,14.4,23.0],"windgusts_10m_max":[16.9,23.8,19.1,39.6,28.4,33.5,56.2],"winddirection_10m_dominant":[307,274,312,350,354,297,278],"shortwave_radiation_sum":[27.53,22.35,24.96,29.02,25.92,28.64,25.66],"et0_fao_evapotranspiration":[4.99,4.39,5.39,5.51,4.61,5.35,5.90]}}